communism/__init__.py
communism/communism.py
communism/stalin.py
communism-0.0.4.dist-info/METADATA
communism-0.0.4.dist-info/RECORD
communism-0.0.4.dist-info/WHEEL
communism-0.0.4.dist-info/top_level.txt
