Metadata-Version: 2.1
Name: communism
Version: 0.0.4
Summary: The best package on PyPi
Home-page: UNKNOWN
Author: Karl Marx
Author-email: dacurse0@gmail.com
License: UNKNOWN
Platform: UNKNOWN
